earth_extractor/__init__.py
earth_extractor/app.py
earth_extractor/cli_options.py
earth_extractor/core/__init__.py
earth_extractor/core/config.py
earth_extractor/core/credentials.py
earth_extractor/core/logging.py
earth_extractor/core/models.py
earth_extractor/core/query.py
earth_extractor/core/utils.py
earth_extractor/providers/__init__.py
earth_extractor/providers/alaskan_satellite_facility.py
earth_extractor/providers/base.py
earth_extractor/providers/copernicus.py
earth_extractor/providers/extensions/__init__.py
earth_extractor/providers/extensions/asf_search.py
earth_extractor/providers/nasa.py
earth_extractor/providers/swisstopo.py
earth_extractor/satellites/__init__.py
earth_extractor/satellites/base.py
earth_extractor/satellites/enums.py
earth_extractor/satellites/modis.py
earth_extractor/satellites/sentinel.py
earth_extractor/satellites/swissimage.py
earth_extractor/satellites/viirs.py
earth_extractor-0.2.0.dist-info/METADATA
earth_extractor-0.2.0.dist-info/WHEEL
earth_extractor-0.2.0.dist-info/entry_points.txt
earth_extractor-0.2.0.dist-info/RECORD
