Metadata-Version: 2.1
Name: earth-extractor
Version: 0.2.0
Summary: A library to simplify the workflow of data acquisition from multiple satellite data providers
Author: Evan Thomas
Author-email: evan.thomas@epfl.ch
Requires-Python: >=3.8,<4.0
Classifier: Programming Language :: Python :: 3
Classifier: Programming Language :: Python :: 3.8
Classifier: Programming Language :: Python :: 3.9
Classifier: Programming Language :: Python :: 3.10
Classifier: Programming Language :: Python :: 3.11
Requires-Dist: aiohttp (>=3.8.5,<4.0.0)
Requires-Dist: asf-search (>=7.0.4,<8.0.0)
Requires-Dist: botocore (==1.29.133)
Requires-Dist: geojson (>=3.1.0,<4.0.0)
Requires-Dist: geopandas (>=0.13.2,<0.14.0)
Requires-Dist: keyring (>=24.2.0,<25.0.0)
Requires-Dist: orjson (>=3.9.5,<4.0.0)
Requires-Dist: pydantic[dotenv] (>=1.10.9,<2.0.0)
Requires-Dist: pyjwt (>=2.8.0,<3.0.0)
Requires-Dist: pystac-client (>=0.7.2,<0.8.0)
Requires-Dist: rich (>=13.3.5,<14.0.0)
Requires-Dist: shapely (>=2.0.1,<3.0.0)
Requires-Dist: tenacity (>=8.2.2,<9.0.0)
Requires-Dist: tqdm (>=4.66.1,<5.0.0)
Requires-Dist: typer (>=0.9.0,<0.10.0)
Requires-Dist: types-requests (>=2.31.0.2,<3.0.0.0)
